.gitignore
AUTHORS
COPYING
MANIFEST.in
README.md
hideezctl
requirements-dev.txt
requirements.txt
setup.cfg
setup.py
bash_completion.d/hideezctl.sh
hideez.egg-info/PKG-INFO
hideez.egg-info/SOURCES.txt
hideez.egg-info/dependency_links.txt
hideez.egg-info/not-zip-safe
hideez.egg-info/requires.txt
hideez.egg-info/top_level.txt
hideezlib/__init__.py
hideezlib/_ed25519.py
hideezlib/client.py
hideezlib/coins.json
hideezlib/coins.py
hideezlib/cosi.py
hideezlib/log.py
hideezlib/mapping.py
hideezlib/protobuf.py
hideezlib/tools.py
hideezlib/tx_api.py
hideezlib/messages/Address.py
hideezlib/messages/ApplyFlags.py
hideezlib/messages/ApplySettings.py
hideezlib/messages/BackupDevice.py
hideezlib/messages/ButtonAck.py
hideezlib/messages/ButtonRequest.py
hideezlib/messages/ButtonRequestType.py
hideezlib/messages/Cancel.py
hideezlib/messages/ChangePin.py
hideezlib/messages/CipherKeyValue.py
hideezlib/messages/CipheredKeyValue.py
hideezlib/messages/ClearSession.py
hideezlib/messages/CosiCommit.py
hideezlib/messages/CosiCommitment.py
hideezlib/messages/CosiSign.py
hideezlib/messages/CosiSignature.py
hideezlib/messages/DebugLinkDecision.py
hideezlib/messages/DebugLinkFlashErase.py
hideezlib/messages/DebugLinkGetState.py
hideezlib/messages/DebugLinkLog.py
hideezlib/messages/DebugLinkMemory.py
hideezlib/messages/DebugLinkMemoryRead.py
hideezlib/messages/DebugLinkMemoryWrite.py
hideezlib/messages/DebugLinkState.py
hideezlib/messages/DebugLinkStop.py
hideezlib/messages/DecryptMessage.py
hideezlib/messages/DecryptedMessage.py
hideezlib/messages/ECDHSessionKey.py
hideezlib/messages/EncryptMessage.py
hideezlib/messages/EncryptedMessage.py
hideezlib/messages/Entropy.py
hideezlib/messages/EntropyAck.py
hideezlib/messages/EntropyRequest.py
hideezlib/messages/EstimateTxSize.py
hideezlib/messages/Failure.py
hideezlib/messages/FailureType.py
hideezlib/messages/Features.py
hideezlib/messages/FirmwareErase.py
hideezlib/messages/FirmwareRequest.py
hideezlib/messages/FirmwareUpload.py
hideezlib/messages/GetAddress.py
hideezlib/messages/GetECDHSessionKey.py
hideezlib/messages/GetEntropy.py
hideezlib/messages/GetFeatures.py
hideezlib/messages/GetPublicKey.py
